toya/__init__.py
toya/config.py
toya/tpl.py
toya/supplier/__init__.py
toya/supplier/env_supplier.py
toya/supplier/mapping_supplier.py
toya/supplier/supplier.py
toya/supplier/yaml_supplier.py
toya-1.0.3.dist-info/METADATA
toya-1.0.3.dist-info/WHEEL
toya-1.0.3.dist-info/licenses/LICENSE
toya-1.0.3.dist-info/RECORD
