Metadata-Version: 2.4
Name: toya
Version: 1.0.3
Summary: Configuration management with deferred binding and value templating
Project-URL: Homepage, https://github.com/cs0ip/toya
Author-email: Sergei Galushkin <cs0ip@ya.ru>
License-Expression: MIT
License-File: LICENSE
Classifier: Development Status :: 5 - Production/Stable
Classifier: Operating System :: OS Independent
Classifier: Programming Language :: Python :: 3
Classifier: Programming Language :: Python :: 3 :: Only
Classifier: Programming Language :: Python :: 3.13
Classifier: Topic :: File Formats
Classifier: Topic :: Software Development :: Libraries
Classifier: Typing :: Typed
Requires-Python: >=3.13
Requires-Dist: jinja2>=3.1.6
Requires-Dist: mergedeep>=1.3.4
Requires-Dist: pyyaml>=6.0.2
